hurnet_fx/__init__.py
hurnet_fx/hurnet_fx.py
hurnet_fx-1.0.2.dist-info/LICENSE.txt
hurnet_fx-1.0.2.dist-info/METADATA
hurnet_fx-1.0.2.dist-info/WHEEL
hurnet_fx-1.0.2.dist-info/top_level.txt
hurnet_fx-1.0.2.dist-info/RECORD
